airflow_provider_ibm_db2/__init__.py
airflow_provider_ibm_db2/example_dags/example_db2_dag.py
airflow_provider_ibm_db2/hooks/db2.py
airflow_provider_ibm_db2/operators/check.py
airflow_provider_ibm_db2/operators/sql.py
airflow_provider_ibm_db2/operators/stored_procedure.py
airflow_provider_ibm_db2-0.1.2.dist-info/METADATA
airflow_provider_ibm_db2-0.1.2.dist-info/WHEEL
airflow_provider_ibm_db2-0.1.2.dist-info/entry_points.txt
airflow_provider_ibm_db2-0.1.2.dist-info/licenses/LICENSE
airflow_provider_ibm_db2-0.1.2.dist-info/RECORD
