Metadata-Version: 2.4
Name: airflow-provider-ibm-db2
Version: 0.1.2
Summary: Apache Airflow provider for IBM Db2 (Hook + Operators, ibm_db_dbi with pyodbc fallback)
Project-URL: Homepage, https://github.com/armandospxp/airflow-provider-ibm-db2
Project-URL: Repository, https://github.com/armandospxp/airflow-provider-ibm-db2
Project-URL: Issues, https://github.com/armandospxp/airflow-provider-ibm-db2/issues
Author: Armando Rodriguez
License: MIT License
License-File: LICENSE
Classifier: Framework :: Apache Airflow
Classifier: License :: OSI Approved :: MIT License
Classifier: Operating System :: OS Independent
Classifier: Programming Language :: Python :: 3
Classifier: Programming Language :: Python :: 3 :: Only
Classifier: Programming Language :: Python :: 3.7
Classifier: Programming Language :: Python :: 3.8
Classifier: Programming Language :: Python :: 3.9
Classifier: Topic :: Database
Classifier: Topic :: Software Development :: Libraries :: Python Modules
Requires-Python: >=3.7
Requires-Dist: apache-airflow<2.6,>=2.4
Provides-Extra: dev
Requires-Dist: mypy; extra == 'dev'
Requires-Dist: pytest; extra == 'dev'
Requires-Dist: pytest-cov; extra == 'dev'
Requires-Dist: ruff; extra == 'dev'
Requires-Dist: types-pyyaml; extra == 'dev'
